<?xml version="1.0" encoding="UTF-8"?>
<resources>
    <color name="very_important_text">#FF0000</color>
    <color name="very_important_tile">#FFDCDC</color>
    <color name="important_text">#FF7A00</color>
    <color name="important_tile">#FFDBC0</color>
    <color name="today_incomplete_tile">#E2E2E2</color>
    <color name="today_completed_text">#00872E</color>
    <color name="today_completed_tile">#ADFFC9</color>
    <color name="upcoming_text">#0013C2</color>
    <color name="upcoming_tile">#C3C6FF</color>
    <color name="previous_text">#8200BF</color>
    <color name="previous_tile">#E2A6FF</color>
    <color name="partially_important_text">#007A73</color>
    <color name="partially_important_tile">#B6FFF2</color>
    <color name="start_page_desc">#8C8C8C</color>
</resources>

